MANIFEST.in
README.md
setup.py
django_phone_login_fix_version.egg-info/PKG-INFO
django_phone_login_fix_version.egg-info/SOURCES.txt
django_phone_login_fix_version.egg-info/dependency_links.txt
django_phone_login_fix_version.egg-info/requires.txt
django_phone_login_fix_version.egg-info/top_level.txt
phone_login/__init__.py
phone_login/admin.py
phone_login/apps.py
phone_login/models.py
phone_login/serializers.py
phone_login/urls.py
phone_login/utils.py
phone_login/views.py
phone_login/backends/__init__.py
phone_login/backends/phone_backend.py
phone_login/migrations/0001_initial.py
phone_login/migrations/__init__.py