Metadata-Version: 1.1
Name: django-phone-login-fix-version
Version: 0.0.5
Summary: Django Phone Login: Login with OTP (fix version)
Home-page: https://github.com/PyCormick/django-phone-login
Author: Daniil Agarev
Author-email: severustime@gmail.com
License: BSD License
Platform: UNKNOWN
Classifier: Environment :: Web Environment
Classifier: Framework :: Django
Classifier: Intended Audience :: Developers
Classifier: License :: OSI Approved :: BSD License
Classifier: Operating System :: OS Independent
Classifier: Programming Language :: Python
Classifier: Programming Language :: Python :: 3
Classifier: Programming Language :: Python :: 3.2
Classifier: Programming Language :: Python :: 3.3
Classifier: Topic :: Internet :: WWW/HTTP
Classifier: Topic :: Internet :: WWW/HTTP :: Dynamic Content
